rb_commons/__init__.py
rb_commons/broker/__init__.py
rb_commons/broker/consumer.py
rb_commons/configs/__init__.py
rb_commons/configs/config.py
rb_commons/configs/injections.py
rb_commons/configs/rabbitmq.py
rb_commons/configs/v2/__init__.py
rb_commons/configs/v2/config.py
rb_commons/http/__init__.py
rb_commons/http/base_api.py
rb_commons/http/consul.py
rb_commons/http/exceptions.py
rb_commons/orm/__init__.py
rb_commons/orm/enum.py
rb_commons/orm/exceptions.py
rb_commons/orm/managers.py
rb_commons/orm/querysets.py
rb_commons/orm/services.py
rb_commons/permissions/__init__.py
rb_commons/permissions/role_permissions.py
rb_commons/schemes/__init__.py
rb_commons/schemes/jwt.py
rb_commons/schemes/pagination.py
rb_commons/utils/__init__.py
rb_commons/utils/media.py
rb_commons-0.7.23.dist-info/METADATA
rb_commons-0.7.23.dist-info/WHEEL
rb_commons-0.7.23.dist-info/top_level.txt
rb_commons-0.7.23.dist-info/RECORD
