Metadata-Version: 2.4
Name: rb-commons
Version: 0.7.23
Summary: Commons of project and simplified orm based on sqlalchemy.
Home-page: https://github.com/RoboSell-organization/rb-commons
Author: Abdulvoris
Author-email: erkinovabdulvoris101@gmail.com
Classifier: Programming Language :: Python :: 3
Classifier: License :: OSI Approved :: MIT License
Classifier: Operating System :: OS Independent
Requires-Python: >=3.11
Requires-Dist: annotated-types==0.7.0
Requires-Dist: greenlet==3.1.1
Requires-Dist: pydantic<3.0.0,>=1.7.4
Requires-Dist: PyJWT==2.10.1
Requires-Dist: python-dotenv==1.0.1
Requires-Dist: SQLAlchemy==2.0.36
Requires-Dist: fastapi<0.120.0,>=0.115.6
Requires-Dist: aio-pika==9.5.5
Dynamic: author
Dynamic: author-email
Dynamic: classifier
Dynamic: description
Dynamic: description-content-type
Dynamic: home-page
Dynamic: requires-dist
Dynamic: requires-python
Dynamic: summary
